multiply.v
module multiply #(
    parameter WIDTH = 16
)(
    input wire clk, rst, start,
    input wire signed [WIDTH-1:0] multiplier,      // Q
    input wire signed [WIDTH-1:0] multiplicand,    // M
    output reg [2*WIDTH-1:0] product               // A
);

    // Temp Registers
    reg signed [WIDTH-1:0] A, Q, M, M_BAR;
    reg [$clog2(WIDTH+1)-1:0] cnt;
    reg Q_1;

    // FSM States
    localparam [2:0]
        IDLE      = 3'b000,
        INIT      = 3'b001,
        OPERATION = 3'b010,
        SHIFT     = 3'b011,
        DONE      = 3'b100;

    reg [2:0] state;
    reg [2:0] next_state;

    // FSM Control Path
    always @(posedge clk or posedge rst) begin
        if (rst) state <= IDLE;
        // No need to reset values for A, Q, M, M_BAR, cnt, Q_1 as they will be initialized in INIT state.
        else state <= next_state;
    end

    // FSM Control Path - Next State Logic
    always @(*) begin
        // If next_state value is not provided, the synthesis tool assumes value needs to be remembered and hence creates a latch which could cause problems for timing analysis.
        // To avoid this, we assign a default value to next_state at the beginning of the always block.
        next_state = state; // default hold state
        case (state)
            IDLE: if (start) next_state = INIT;
            INIT: next_state = OPERATION;
            OPERATION: next_state = SHIFT;
            SHIFT: next_state = (cnt == 0) ? DONE : OPERATION;
            DONE: next_state = IDLE;
            default: next_state = IDLE;
        endcase
    end

    // FSM Data Path
    always @(posedge clk) begin
        case (state)
            INIT: begin
                A <= 0;
                Q <= multiplier;
                M <= multiplicand;
                M_BAR <= ~multiplicand + 1; // Two's complement
                cnt <= WIDTH-1;
                Q_1 <= 0;
            end
            OPERATION: begin
                case ({Q[0], Q_1})
                    2'b01: A <= A + M;       // A = A + M
                    2'b10: A <= A + M_BAR;   // A = A - M
                    default: ;                // No operation
                endcase
            end
            SHIFT: begin
                Q_1 <= Q[0];
                {A, Q} <= $signed({A, Q}) >>> 1;     // Arithmetic right shift
                cnt <= cnt - 1;
            end
            DONE: begin
                product <= {A, Q};
            end
            default: ;
        endcase
    end
    
endmodule

multiply_tb.v
module multiply_tb();
    reg tb_clk, tb_rst, tb_start;
    reg signed [15:0] tb_multiplier;
    reg signed [15:0] tb_multiplicand;

    wire [31:0] tb_product;

    multiply u_multiply (
        .clk(tb_clk),
        .rst(tb_rst),
        .start(tb_start),
        .multiplier(tb_multiplier),
        .multiplicand(tb_multiplicand),
        .product(tb_product)
    );

    // Clock generation
    initial begin
        tb_clk = 0;
        forever #5 tb_clk = ~tb_clk; // 10 time units clock period
    end
    // Testbench procedure
    // 1. 12;  2. 0;  3. -1; 4. 0;  5. 882;  6. -108
    initial begin
        // Initialize inputs
        tb_rst = 1;
        tb_start = 0;
        tb_multiplier = 0;
        tb_multiplicand = 0;

        // Release reset
        #15;
        tb_rst = 0;

        // Time required for each testcase - 
        // 1. 1 cycle for INIT
        // 2. 16x2 cycles for OPERATION and SHIFT (each takes 1 cycle and is done 16 times)
        // 3. 1 cycle for DONE
        // 4. Total = 34 cycles = 340 time units

        // Test case 1
        #10;
        tb_multiplier = 16'sd3;     // sd - signed decimal
        tb_multiplicand = 16'sd4;
        tb_start = 1;
        #10;
        tb_start = 0;

        // Wait for operation to complete
        #400;

        // Test case 2
        #10;
        tb_multiplier = -16'sd0;
        tb_multiplicand = 16'sd0;
        tb_start = 1;
        #10;
        tb_start = 0;
        #400;

        // Test case 3
        #10;
        tb_multiplier = -16'sd1;
        tb_multiplicand = 16'sd1;
        tb_start = 1;
        #10;
        tb_start = 0;
        #400;

        // Test case 4
        #10;
        tb_multiplier = -16'sd1;
        tb_multiplicand = 16'sd0;
        tb_start = 1;
        #10;
        tb_start = 0;
        #400;

        // Test case 5
        #10;
        tb_multiplier = -16'sd42;
        tb_multiplicand = -16'sd21;
        tb_start = 1;
        #10;
        tb_start = 0;
        #400;

        // Test case 6
        #10;
        tb_multiplier = 16'sd9;
        tb_multiplicand = -16'sd12;
        tb_start = 1;
        #10;
        tb_start = 0;
        #400;

        // Finish simulation
        $finish;
    end

    initial begin
        $monitor("Time: %0t | Multiplier (Q): %d | Multiplicand (M): %d | Product: %d", 
                  $time, tb_multiplier, tb_multiplicand, tb_product);
    end

    initial begin
        $dumpfile("multiply_tb.vcd");
        $dumpvars(0, multiply_tb);
    end
endmodule

multiply_tb.vcd
$date
	Wed Feb  4 21:41:02 2026
$end
$version
	Icarus Verilog
$end
$timescale
	1s
$end
$scope module multiply_tb $end
$var wire 32 ! tb_product [31:0] $end
$var reg 1 " tb_clk $end
$var reg 16 # tb_multiplicand [15:0] $end
$var reg 16 $ tb_multiplier [15:0] $end
$var reg 1 % tb_rst $end
$var reg 1 & tb_start $end
$scope module u_multiply $end
$var wire 1 " clk $end
$var wire 16 ' multiplicand [15:0] $end
$var wire 16 ( multiplier [15:0] $end
$var wire 1 % rst $end
$var wire 1 & start $end
$var parameter 3 ) DONE $end
$var parameter 3 * IDLE $end
$var parameter 3 + INIT $end
$var parameter 3 , OPERATION $end
$var parameter 3 - SHIFT $end
$var parameter 32 . WIDTH $end
$var reg 16 / A [15:0] $end
$var reg 16 0 M [15:0] $end
$var reg 16 1 M_BAR [15:0] $end
$var reg 16 2 Q [15:0] $end
$var reg 1 3 Q_1 $end
$var reg 5 4 cnt [4:0] $end
$var reg 3 5 next_state [2:0] $end
$var reg 32 6 product [31:0] $end
$var reg 3 7 state [2:0] $end
$upscope $end
$upscope $end
$enddefinitions $end
$comment Show the parameter values. $end
$dumpall
b10000 .
b11 -
b10 ,
b1 +
b0 *
b100 )
$end
#0
$dumpvars
b0 7
bx 6
b0 5
bx 4
x3
bx 2
bx 1
bx 0
bx /
b0 (
b0 '
0&
1%
b0 $
b0 #
0"
bx !
$end
#5
1"
#10
0"
#15
1"
0%
#20
0"
#25
b1 7
b10 5
1"
1&
b100 #
b100 '
b11 $
b11 (
#30
0"
#35
03
b1111 4
b1111111111111100 1
b100 0
b11 2
b0 /
b10 7
b11 5
1"
0&
#40
0"
#45
b10 5
b1111111111111100 /
b11 7
1"
#50
0"
#55
b11 5
b1110 4
b1111111111111110 /
b1 2
13
b10 7
1"
#60
0"
#65
b10 5
b11 7
1"
#70
0"
#75
b11 5
b1101 4
b1111111111111111 /
b0 2
b10 7
1"
#80
0"
#85
b10 5
b11 /
b11 7
1"
#90
0"
#95
b11 5
b1100 4
b1 /
b1000000000000000 2
03
b10 7
1"
#100
0"
#105
b10 5
b11 7
1"
#110
0"
#115
b11 5
b1011 4
b0 /
b1100000000000000 2
b10 7
1"
#120
0"
#125
b10 5
b11 7
1"
#130
0"
#135
b11 5
b1010 4
b110000000000000 2
b10 7
1"
#140
0"
#145
b10 5
b11 7
1"
#150
0"
#155
b11 5
b1001 4
b11000000000000 2
b10 7
1"
#160
0"
#165
b10 5
b11 7
1"
#170
0"
#175
b11 5
b1000 4
b1100000000000 2
b10 7
1"
#180
0"
#185
b10 5
b11 7
1"
#190
0"
#195
b11 5
b111 4
b110000000000 2
b10 7
1"
#200
0"
#205
b10 5
b11 7
1"
#210
0"
#215
b11 5
b110 4
b11000000000 2
b10 7
1"
#220
0"
#225
b10 5
b11 7
1"
#230
0"
#235
b11 5
b101 4
b1100000000 2
b10 7
1"
#240
0"
#245
b10 5
b11 7
1"
#250
0"
#255
b11 5
b100 4
b110000000 2
b10 7
1"
#260
0"
#265
b10 5
b11 7
1"
#270
0"
#275
b11 5
b11 4
b11000000 2
b10 7
1"
#280
0"
#285
b10 5
b11 7
1"
#290
0"
#295
b11 5
b10 4
b1100000 2
b10 7
1"
#300
0"
#305
b10 5
b11 7
1"
#310
0"
#315
b11 5
b1 4
b110000 2
b10 7
1"
#320
0"
#325
b10 5
b11 7
1"
#330
0"
#335
b11 5
b0 4
b11000 2
b10 7
1"
#340
0"
#345
b100 5
b11 7
1"
#350
0"
#355
b0 5
b11111 4
b1100 2
b100 7
1"
#360
0"
#365
b1100 !
b1100 6
b0 7
1"
#370
0"
#375
1"
#380
0"
#385
1"
#390
0"
#395
1"
#400
0"
#405
1"
#410
0"
#415
1"
#420
0"
#425
1"
#430
0"
#435
1"
#440
0"
#445
b1 7
b10 5
1"
1&
b0 #
b0 '
b0 $
b0 (
#450
0"
#455
b1111 4
b0 1
b0 0
b0 2
b10 7
b11 5
1"
0&
#460
0"
#465
b10 5
b11 7
1"
#470
0"
#475
b11 5
b1110 4
b10 7
1"
#480
0"
#485
b10 5
b11 7
1"
#490
0"
#495
b11 5
b1101 4
b10 7
1"
#500
0"
#505
b10 5
b11 7
1"
#510
0"
#515
b11 5
b1100 4
b10 7
1"
#520
0"
#525
b10 5
b11 7
1"
#530
0"
#535
b11 5
b1011 4
b10 7
1"
#540
0"
#545
b10 5
b11 7
1"
#550
0"
#555
b11 5
b1010 4
b10 7
1"
#560
0"
#565
b10 5
b11 7
1"
#570
0"
#575
b11 5
b1001 4
b10 7
1"
#580
0"
#585
b10 5
b11 7
1"
#590
0"
#595
b11 5
b1000 4
b10 7
1"
#600
0"
#605
b10 5
b11 7
1"
#610
0"
#615
b11 5
b111 4
b10 7
1"
#620
0"
#625
b10 5
b11 7
1"
#630
0"
#635
b11 5
b110 4
b10 7
1"
#640
0"
#645
b10 5
b11 7
1"
#650
0"
#655
b11 5
b101 4
b10 7
1"
#660
0"
#665
b10 5
b11 7
1"
#670
0"
#675
b11 5
b100 4
b10 7
1"
#680
0"
#685
b10 5
b11 7
1"
#690
0"
#695
b11 5
b11 4
b10 7
1"
#700
0"
#705
b10 5
b11 7
1"
#710
0"
#715
b11 5
b10 4
b10 7
1"
#720
0"
#725
b10 5
b11 7
1"
#730
0"
#735
b11 5
b1 4
b10 7
1"
#740
0"
#745
b10 5
b11 7
1"
#750
0"
#755
b11 5
b0 4
b10 7
1"
#760
0"
#765
b100 5
b11 7
1"
#770
0"
#775
b0 5
b11111 4
b100 7
1"
#780
0"
#785
b0 !
b0 6
b0 7
1"
#790
0"
#795
1"
#800
0"
#805
1"
#810
0"
#815
1"
#820
0"
#825
1"
#830
0"
#835
1"
#840
0"
#845
1"
#850
0"
#855
1"
#860
0"
#865
b1 7
b10 5
1"
1&
b1 #
b1 '
b1111111111111111 $
b1111111111111111 (
#870
0"
#875
b1111 4
b1111111111111111 1
b1 0
b1111111111111111 2
b10 7
b11 5
1"
0&
#880
0"
#885
b10 5
b1111111111111111 /
b11 7
1"
#890
0"
#895
b11 5
b1110 4
13
b10 7
1"
#900
0"
#905
b10 5
b11 7
1"
#910
0"
#915
b11 5
b1101 4
b10 7
1"
#920
0"
#925
b10 5
b11 7
1"
#930
0"
#935
b11 5
b1100 4
b10 7
1"
#940
0"
#945
b10 5
b11 7
1"
#950
0"
#955
b11 5
b1011 4
b10 7
1"
#960
0"
#965
b10 5
b11 7
1"
#970
0"
#975
b11 5
b1010 4
b10 7
1"
#980
0"
#985
b10 5
b11 7
1"
#990
0"
#995
b11 5
b1001 4
b10 7
1"
#1000
0"
#1005
b10 5
b11 7
1"
#1010
0"
#1015
b11 5
b1000 4
b10 7
1"
#1020
0"
#1025
b10 5
b11 7
1"
#1030
0"
#1035
b11 5
b111 4
b10 7
1"
#1040
0"
#1045
b10 5
b11 7
1"
#1050
0"
#1055
b11 5
b110 4
b10 7
1"
#1060
0"
#1065
b10 5
b11 7
1"
#1070
0"
#1075
b11 5
b101 4
b10 7
1"
#1080
0"
#1085
b10 5
b11 7
1"
#1090
0"
#1095
b11 5
b100 4
b10 7
1"
#1100
0"
#1105
b10 5
b11 7
1"
#1110
0"
#1115
b11 5
b11 4
b10 7
1"
#1120
0"
#1125
b10 5
b11 7
1"
#1130
0"
#1135
b11 5
b10 4
b10 7
1"
#1140
0"
#1145
b10 5
b11 7
1"
#1150
0"
#1155
b11 5
b1 4
b10 7
1"
#1160
0"
#1165
b10 5
b11 7
1"
#1170
0"
#1175
b11 5
b0 4
b10 7
1"
#1180
0"
#1185
b100 5
b11 7
1"
#1190
0"
#1195
b0 5
b11111 4
b100 7
1"
#1200
0"
#1205
b11111111111111111111111111111111 !
b11111111111111111111111111111111 6
b0 7
1"
#1210
0"
#1215
1"
#1220
0"
#1225
1"
#1230
0"
#1235
1"
#1240
0"
#1245
1"
#1250
0"
#1255
1"
#1260
0"
#1265
1"
#1270
0"
#1275
1"
#1280
0"
#1285
b1 7
b10 5
1"
1&
b0 #
b0 '
#1290
0"
#1295
03
b1111 4
b0 1
b0 0
b0 /
b10 7
b11 5
1"
0&
#1300
0"
#1305
b10 5
b11 7
1"
#1310
0"
#1315
b11 5
b1110 4
b111111111111111 2
13
b10 7
1"
#1320
0"
#1325
b10 5
b11 7
1"
#1330
0"
#1335
b11 5
b1101 4
b11111111111111 2
b10 7
1"
#1340
0"
#1345
b10 5
b11 7
1"
#1350
0"
#1355
b11 5
b1100 4
b1111111111111 2
b10 7
1"
#1360
0"
#1365
b10 5
b11 7
1"
#1370
0"
#1375
b11 5
b1011 4
b111111111111 2
b10 7
1"
#1380
0"
#1385
b10 5
b11 7
1"
#1390
0"
#1395
b11 5
b1010 4
b11111111111 2
b10 7
1"
#1400
0"
#1405
b10 5
b11 7
1"
#1410
0"
#1415
b11 5
b1001 4
b1111111111 2
b10 7
1"
#1420
0"
#1425
b10 5
b11 7
1"
#1430
0"
#1435
b11 5
b1000 4
b111111111 2
b10 7
1"
#1440
0"
#1445
b10 5
b11 7
1"
#1450
0"
#1455
b11 5
b111 4
b11111111 2
b10 7
1"
#1460
0"
#1465
b10 5
b11 7
1"
#1470
0"
#1475
b11 5
b110 4
b1111111 2
b10 7
1"
#1480
0"
#1485
b10 5
b11 7
1"
#1490
0"
#1495
b11 5
b101 4
b111111 2
b10 7
1"
#1500
0"
#1505
b10 5
b11 7
1"
#1510
0"
#1515
b11 5
b100 4
b11111 2
b10 7
1"
#1520
0"
#1525
b10 5
b11 7
1"
#1530
0"
#1535
b11 5
b11 4
b1111 2
b10 7
1"
#1540
0"
#1545
b10 5
b11 7
1"
#1550
0"
#1555
b11 5
b10 4
b111 2
b10 7
1"
#1560
0"
#1565
b10 5
b11 7
1"
#1570
0"
#1575
b11 5
b1 4
b11 2
b10 7
1"
#1580
0"
#1585
b10 5
b11 7
1"
#1590
0"
#1595
b11 5
b0 4
b1 2
b10 7
1"
#1600
0"
#1605
b100 5
b11 7
1"
#1610
0"
#1615
b0 5
b11111 4
b0 2
b100 7
1"
#1620
0"
#1625
b0 !
b0 6
b0 7
1"
#1630
0"
#1635
1"
#1640
0"
#1645
1"
#1650
0"
#1655
1"
#1660
0"
#1665
1"
#1670
0"
#1675
1"
#1680
0"
#1685
1"
#1690
0"
#1695
1"
#1700
0"
#1705
b1 7
b10 5
1"
1&
b1111111111101011 #
b1111111111101011 '
b1111111111010110 $
b1111111111010110 (
#1710
0"
#1715
03
b1111 4
b10101 1
b1111111111101011 0
b1111111111010110 2
b10 7
b11 5
1"
0&
#1720
0"
#1725
b10 5
b11 7
1"
#1730
0"
#1735
b11 5
b1110 4
b111111111101011 2
b10 7
1"
#1740
0"
#1745
b10 5
b10101 /
b11 7
1"
#1750
0"
#1755
b11 5
b1101 4
b1010 /
b1011111111110101 2
13
b10 7
1"
#1760
0"
#1765
b10 5
b11 7
1"
#1770
0"
#1775
b11 5
b1100 4
b101 /
b101111111111010 2
b10 7
1"
#1780
0"
#1785
b10 5
b1111111111110000 /
b11 7
1"
#1790
0"
#1795
b11 5
b1011 4
b1111111111111000 /
b10111111111101 2
03
b10 7
1"
#1800
0"
#1805
b10 5
b1101 /
b11 7
1"
#1810
0"
#1815
b11 5
b1010 4
b110 /
b1001011111111110 2
13
b10 7
1"
#1820
0"
#1825
b10 5
b1111111111110001 /
b11 7
1"
#1830
0"
#1835
b11 5
b1001 4
b1111111111111000 /
b1100101111111111 2
03
b10 7
1"
#1840
0"
#1845
b10 5
b1101 /
b11 7
1"
#1850
0"
#1855
b11 5
b1000 4
b110 /
b1110010111111111 2
13
b10 7
1"
#1860
0"
#1865
b10 5
b11 7
1"
#1870
0"
#1875
b11 5
b111 4
b11 /
b111001011111111 2
b10 7
1"
#1880
0"
#1885
b10 5
b11 7
1"
#1890
0"
#1895
b11 5
b110 4
b1 /
b1011100101111111 2
b10 7
1"
#1900
0"
#1905
b10 5
b11 7
1"
#1910
0"
#1915
b11 5
b101 4
b0 /
b1101110010111111 2
b10 7
1"
#1920
0"
#1925
b10 5
b11 7
1"
#1930
0"
#1935
b11 5
b100 4
b110111001011111 2
b10 7
1"
#1940
0"
#1945
b10 5
b11 7
1"
#1950
0"
#1955
b11 5
b11 4
b11011100101111 2
b10 7
1"
#1960
0"
#1965
b10 5
b11 7
1"
#1970
0"
#1975
b11 5
b10 4
b1101110010111 2
b10 7
1"
#1980
0"
#1985
b10 5
b11 7
1"
#1990
0"
#1995
b11 5
b1 4
b110111001011 2
b10 7
1"
#2000
0"
#2005
b10 5
b11 7
1"
#2010
0"
#2015
b11 5
b0 4
b11011100101 2
b10 7
1"
#2020
0"
#2025
b100 5
b11 7
1"
#2030
0"
#2035
b0 5
b11111 4
b1101110010 2
b100 7
1"
#2040
0"
#2045
b1101110010 !
b1101110010 6
b0 7
1"
#2050
0"
#2055
1"
#2060
0"
#2065
1"
#2070
0"
#2075
1"
#2080
0"
#2085
1"
#2090
0"
#2095
1"
#2100
0"
#2105
1"
#2110
0"
#2115
1"
#2120
0"
#2125
b1 7
b10 5
1"
1&
b1111111111110100 #
b1111111111110100 '
b1001 $
b1001 (
#2130
0"
#2135
03
b1111 4
b1100 1
b1111111111110100 0
b1001 2
b10 7
b11 5
1"
0&
#2140
0"
#2145
b10 5
b1100 /
b11 7
1"
#2150
0"
#2155
b11 5
b1110 4
b110 /
b100 2
13
b10 7
1"
#2160
0"
#2165
b10 5
b1111111111111010 /
b11 7
1"
#2170
0"
#2175
b11 5
b1101 4
b1111111111111101 /
b10 2
03
b10 7
1"
#2180
0"
#2185
b10 5
b11 7
1"
#2190
0"
#2195
b11 5
b1100 4
b1111111111111110 /
b1000000000000001 2
b10 7
1"
#2200
0"
#2205
b10 5
b1010 /
b11 7
1"
#2210
0"
#2215
b11 5
b1011 4
b101 /
b100000000000000 2
13
b10 7
1"
#2220
0"
#2225
b10 5
b1111111111111001 /
b11 7
1"
#2230
0"
#2235
b11 5
b1010 4
b1111111111111100 /
b1010000000000000 2
03
b10 7
1"
#2240
0"
#2245
b10 5
b11 7
1"
#2250
0"
#2255
b11 5
b1001 4
b1111111111111110 /
b101000000000000 2
b10 7
1"
#2260
0"
#2265
b10 5
b11 7
1"
#2270
0"
#2275
b11 5
b1000 4
b1111111111111111 /
b10100000000000 2
b10 7
1"
#2280
0"
#2285
b10 5
b11 7
1"
#2290
0"
#2295
b11 5
b111 4
b1001010000000000 2
b10 7
1"
#2300
0"
#2305
b10 5
b11 7
1"
#2310
0"
#2315
b11 5
b110 4
b1100101000000000 2
b10 7
1"
#2320
0"
#2325
b10 5
b11 7
1"
#2330
0"
#2335
b11 5
b101 4
b1110010100000000 2
b10 7
1"
#2340
0"
#2345
b10 5
b11 7
1"
#2350
0"
#2355
b11 5
b100 4
b1111001010000000 2
b10 7
1"
#2360
0"
#2365
b10 5
b11 7
1"
#2370
0"
#2375
b11 5
b11 4
b1111100101000000 2
b10 7
1"
#2380
0"
#2385
b10 5
b11 7
1"
#2390
0"
#2395
b11 5
b10 4
b1111110010100000 2
b10 7
1"
#2400
0"
#2405
b10 5
b11 7
1"
#2410
0"
#2415
b11 5
b1 4
b1111111001010000 2
b10 7
1"
#2420
0"
#2425
b10 5
b11 7
1"
#2430
0"
#2435
b11 5
b0 4
b1111111100101000 2
b10 7
1"
#2440
0"
#2445
b100 5
b11 7
1"
#2450
0"
#2455
b0 5
b11111 4
b1111111110010100 2
b100 7
1"
#2460
0"
#2465
b11111111111111111111111110010100 !
b11111111111111111111111110010100 6
b0 7
1"
